MANIFEST.in
README.md
setup.py
cfclon/__init__.py
cfclon/bary.py
cfclon/scan.py
cfclon.egg-info/PKG-INFO
cfclon.egg-info/SOURCES.txt
cfclon.egg-info/dependency_links.txt
cfclon.egg-info/not-zip-safe
cfclon.egg-info/requires.txt
cfclon.egg-info/top_level.txt