Metadata-Version: 2.1
Name: cfclon
Version: 0.1
Summary: Complex functions course character cloning project
Author: Samy Zafrany
Author-email: sz@samyzaf.com
License: MIT
Keywords: barycentric coordinates,mean value coordinates,harmonic coordinates
